sk_report_generator/__init__.py
sk_report_generator/reporter/__init__.py
sk_report_generator/reporter/base.py
sk_report_generator/reporter/default.py
sk_report_generator/reporter/format.py
sk_report_generator/reporter/function.py
sk_report_generator/reporter/operation.py
sk_report_generator/reporter/script.py
sk_report_generator/reporter/formatter/__init__.py
sk_report_generator/reporter/formatter/base.py
sk_report_generator/reporter/formatter/custom_format.py
sk_report_generator/reporter/formatter/default_format_evaluate.py
sk_report_generator/reporter/formatter/format_default.py
sk_report_generator/reporter/formatter/format_evaluate.py
sk_report_generator/reporter/formatter/custom_format_functions/__init__.py
sk_report_generator/reporter/formatter/custom_format_functions/bool.py
sk_report_generator/reporter/formatter/custom_format_functions/ceil.py
sk_report_generator/reporter/formatter/custom_format_functions/currency.py
sk_report_generator/reporter/formatter/custom_format_functions/datetime.py
sk_report_generator/reporter/formatter/custom_format_functions/default.py
sk_report_generator/reporter/formatter/custom_format_functions/floor.py
sk_report_generator/reporter/formatter/custom_format_functions/mask.py
sk_report_generator/reporter/formatter/custom_format_functions/round.py
sk_report_generator/reporter/formatter/custom_format_functions/str_continue.py
sk_report_generator/reporter/formatter/custom_format_functions/trunc.py
sk_report_generator/reporter/formatter/json_to_format_spec/__init__.py
sk_report_generator/reporter/formatter/json_to_format_spec/align.py
sk_report_generator/reporter/formatter/json_to_format_spec/dufault.py
sk_report_generator/reporter/formatter/json_to_format_spec/fill.py
sk_report_generator/reporter/formatter/json_to_format_spec/grouping_option.py
sk_report_generator/reporter/formatter/json_to_format_spec/pad.py
sk_report_generator/reporter/formatter/json_to_format_spec/precision.py
sk_report_generator-1.0.102.dist-info/LICENSE.txt
sk_report_generator-1.0.102.dist-info/METADATA
sk_report_generator-1.0.102.dist-info/WHEEL
sk_report_generator-1.0.102.dist-info/top_level.txt
sk_report_generator-1.0.102.dist-info/RECORD
